Tool.py
mytestlib/__init__.py
mytestlib/my_lib_one.py
mytestpro-1.0.0.dist-info/METADATA
mytestpro-1.0.0.dist-info/RECORD
mytestpro-1.0.0.dist-info/WHEEL
mytestpro-1.0.0.dist-info/top_level.txt
