Metadata-Version: 2.1
Name: mytestpro
Version: 1.0.0
Summary: this a very niubi lib
Home-page: https://www.baidu.com/
Author: ----Z--
Author-email: lz5215560@163.com
License: UNKNOWN
Platform: UNKNOWN
